Workbook

Sheet United Spirits IS
B3: United Spirits Limited - Consolidated Income Statement ('INR Crore) | I3: United Spirits Limited - Common Size Income Statement
C4: Consolidated Income Statement | D4: March 31, 2025 | E4: March 31, 2024 | F4: March 31, 2023 | G4: March 31, 2022 | I4: Consolidated Income Statement | J4: March 31, 2025 | K4: March 31, 2024 | L4: March 31, 2023 | M4: March 31, 2022
B5: Revenue or Sales | C5: Revenue from Operations | D5: 26780 | E5: 25389 | F5: 27578 | G5: 30773 | I5: Total Revenue or Income | J5: 27206 | K5: 25724 | L5: 27652 | M5: 30807
C6: Other Income | D6: 426 | E6: 335 | F6: 74 | G6: 34 | I6: Cost of Materials Consumed | J6: =D8/J5 -> 0.20006616 | K6: =E8/K5 -> 0.20424506 | L6: =F8/L5 -> 0.19300593 | M6: =G8/M5 -> 0.15545168
C7: Total Revenue or Income | D7: =SUM(D5:D6) -> 27206 | E7: =SUM(E5:E6) -> 25724 | F7: =SUM(F5:F6) -> 27652 | G7: =SUM(G5:G6) -> 30807 | I7: Purchase of Stock-in-Trade | J7: =D9/J5 -> 0.031757701 | K7: =E9/K5 -> 0.026240087 | L7: =F9/L5 -> 0.03124548 | M7: =G9/M5 -> 0.01872951
B8: Cost Of Goods Sold (COGS) | C8: Cost of Materials Consumed | D8: 5443 | E8: 5254 | F8: 5337 | G8: 4789 | I8: Total COGS | J8: =D12/J5 -> 0.79408954 | K8: =E12/K5 -> 0.80644534 | L8: =F12/L5 -> 0.84174743 | M8: =G12/M5 -> 0.86447885
C9: Purchase of Stock-in-Trade | D9: 864 | E9: 675 | F9: 864 | G9: 577 | I9: Gross Profit | J9: =D13/J5 -> 0.20591046 | K9: =E13/K5 -> 0.19355466 | L9: =F13/L5 -> 0.15825257 | M9: =G13/M5 -> 0.13552115
C10: Change in Inventories of Finished Goods, Work-in-Progress and Stock-in-Trade | D10: 90 | E10: 119 | F10: -129 | G10: -83 | I10: Employee Benefits Expense | J10: =D15/J5 -> 0.022237742 | K10: =E15/K5 -> 0.021108692 | L10: =F15/L5 -> 0.021951396 | M10: =G15/M5 -> 0.021099101
C11: Excise Duty | D11: 15207 | E11: 14697 | F11: 17204 | G11: 21349 | I11: Depreciation and Amortisation Expense | J11: =D16/J5 -> 0.010071308 | K11: =E16/K5 -> 0.01026279 | L11: =F16/L5 -> 0.0098003761 | M11: =G16/M5 -> 0.0093809848
C12: Total COGS | D12: =SUM(D8:D11) -> 21604 | E12: =SUM(E8:E11) -> 20745 | F12: =SUM(F8:F11) -> 23276 | G12: =SUM(G8:G11) -> 26632 | I12: Other Expenses | J12: =D17/J5 -> 0.09236933 | K12: =E17/K5 -> 0.093025968 | L12: =F17/L5 -> 0.082308694 | M12: =G17/M5 -> 0.064271107
B13: Revenue - COGS | C13: Gross Profit | D13: =D7-D12 -> 5602 | E13: =E7-E12 -> 4979 | F13: =F7-F12 -> 4376 | G13: =G7-G12 -> 4175 | I13: Total OPEX | J13: =D18/J5 -> 0.12467838 | K13: =E18/K5 -> 0.12439745 | L13: =F18/L5 -> 0.11406047 | M13: =G18/M5 -> 0.094751193
I14: Operating Profit or Earnings Before Interest and Taxes (EBIT) | J14: =D19/J5 -> 0.081232081 | K14: =E19/K5 -> 0.069157207 | L14: =F19/L5 -> 0.044192102 | M14: =G19/M5 -> 0.040769955
B15: Operating Expenses (OPEX) | C15: Employee Benefits Expense | D15: 605 | E15: 543 | F15: 607 | G15: 650 | I15: Finance Costs | J15: =D21/J5 -> 0.0032713372 | K15: =E21/K5 -> 0.0029544394 | L15: =F21/L5 -> 0.0037610299 | M15: =G21/M5 -> 0.0028564937
C16: Depreciation and Amortisation Expense | D16: 274 | E16: 264 | F16: 271 | G16: 289 | I16: Add/(Less): Exceptional Items, Net | J16: =D22/J5 -> -0.0023891789 | K16: =E22/K5 -> -0.00066086145 | L16: =F22/L5 -> 0.0061840012 | M16: =G22/M5 -> -0.0050637842
C17: Other Expenses | D17: 2513 | E17: 2393 | F17: 2276 | G17: 1980 | I17: Profit Before Tax (PBT) | J17: =D23/J5 -> 0.075571565 | K17: =E23/K5 -> 0.065541906 | L17: =F23/L5 -> 0.046615073 | M17: =G23/M5 -> 0.032849677
C18: Total OPEX | D18: =SUM(D15:D17) -> 3392 | E18: =SUM(E15:E17) -> 3200 | F18: =SUM(F15:F17) -> 3154 | G18: =SUM(G15:G17) -> 2919 | I18: Current Tax | J18: =D25/J5 -> 0.01793722 | K18: =E25/K5 -> 0.015277562 | L18: =F25/L5 -> 0.0091132649 | M18: =G25/M5 -> 0.0048365631
B19: Gross Profit - OPEX | C19: Operating Profit or Earnings Before Interest and Taxes (EBIT) | D19: =D13-D18 -> 2210 | E19: =E13-E18 -> 1779 | F19: =F13-F18 -> 1222 | G19: =G13-G18 -> 1256 | I19: Deferred tax | J19: =D26/J5 -> 0.00036756598 | K19: =E26/K5 -> -0.00073860986 | L19: =F26/L5 -> -0.00054245624 | M19: =G26/M5 -> 0.00038952186
I20: Total Tax Expense | J20: =D27/J5 -> 0.018304786 | K20: =E27/K5 -> 0.014538952 | L20: =F27/L5 -> 0.0085708086 | M20: =G27/M5 -> 0.005226085
B21: Interest | C21: Finance Costs | D21: 89 | E21: 76 | F21: 104 | G21: 88 | I21: Net Income or Proft After Tax (PAT) | J21: =D28/J5 -> 0.057266779 | K21: =E28/K5 -> 0.051002954 | L21: =F28/L5 -> 0.038044264 | M21: =G28/M5 -> 0.027623592
B22: Non-Operating Income | C22: Add/(Less): Exceptional Items, Net | D22: -65 | E22: -17 | F22: 171 | G22: -156
B23: EBIT - Interest + Non-Operating Income | C23: Profit Before Tax (PBT) | D23: =D19-D21+D22 -> 2056 | E23: =E19-E21+E22 -> 1686 | F23: =F19-F21+F22 -> 1289 | G23: =G19-G21+G22 -> 1012
B25: Tax Expense | C25: Current Tax | D25: 488 | E25: 393 | F25: 252 | G25: 149
C26: Deferred tax | D26: 10 | E26: -19 | F26: -15 | G26: 12
C27: Total Tax Expense | D27: =D25+D26 -> 498 | E27: =E25+E26 -> 374 | F27: =F25+F26 -> 237 | G27: =G25+G26 -> 161
B28: PBT - Tax | C28: Net Income or Profit After Tax (PAT) | D28: =D23-D27 -> 1558 | E28: =E23-E27 -> 1312 | F28: =F23-F27 -> 1052 | G28: =G23-G27 -> 851

Sheet United Spirits BS
B3: United Spirits Limited - Consolidated Balance Sheet ('INR Crore) | I3: United Spirits Limited - Common Size Balance Sheet
C4: Consolidated Balance Sheet | D4: March 31, 2025 | E4: March 31, 2024 | F4: March 31, 2023 | G4: March 31, 2022 | J4: Consolidated Balance Sheet | K4: March 31, 2025 | L4: March 31, 2024 | M4: March 31, 2023 | N4: March 31, 2022
B6: ASSETS | I6: ASSETS
B8: Non-Current Assets | C8: Property, Plant and Equipment | D8: 850 | E8: 844 | F8: 978 | G8: 1201 | I8: Non-Current Assets | J8: Property, Plant and Equipment | K8: =$D8/$D$22 -> 0.066834408 | L8: =$E8/$E$22 -> 0.078570099 | M8: =$F8/$F$22 -> 0.10218368 | N8: =$G8/$G$22 -> 0.13768199
C9: Intangible Assets | D9: 24 | E9: 35 | F9: 31 | G9: 25 | J9: Intangible Assets (Goodwill) | K9: =$D9/$D$22 -> 0.0018870892 | L9: =$E9/$E$22 -> 0.0032582387 | M9: =$F9/$F$22 -> 0.003238951 | N9: =$G9/$G$22 -> 0.0028659865
C10: Financial Assets | D10: 958 | E10: 701 | F10: 352 | G10: 365 | J10: Other Intangible Assets (Under Development) | K10: =$D10/$D$22 -> 0.075326309 | L10: =$E10/$E$22 -> 0.065257866 | M10: =$F10/$F$22 -> 0.036777766 | N10: =$G10/$G$22 -> 0.041843403
C11: *Other Non-Current Assets | D11: 2069 | E11: 2144 | F11: 1988 | G11: 1942 | J11: *Other Non-Current Assets | K11: =$D11/$D$22 -> 0.16268281 | L11: =$E11/$E$22 -> 0.19959039 | M11: =$F11/$F$22 -> 0.20771079 | N11: =$G11/$G$22 -> 0.22262983
C12: Total Non-Current Assets | D12: =SUM(D8:D11) -> 3901 | E12: =SUM(E8:E11) -> 3724 | F12: =SUM(F8:F11) -> 3349 | G12: =SUM(G8:G11) -> 3533 | J12: Total Non-Current Assets | K12: =$D12/$D$22 -> 0.30673062 | L12: =$E12/$E$22 -> 0.3466766 | M12: =$F12/$F$22 -> 0.34991119 | N12: =$G12/$G$22 -> 0.40502121
B14: Current Assets | C14: Inventories | D14: 2305 | E14: 2063 | F14: 2230 | G14: 2164 | I14: Current Assets | J14: Inventories | K14: =$D14/$D$22 -> 0.18123919 | L14: =$E14/$E$22 -> 0.1920499 | M14: =$F14/$F$22 -> 0.23299551 | N14: =$G14/$G$22 -> 0.24807979
C15: Trade Receivables (Billed and Unbilled) | D15: 3288 | E15: 2763 | F15: 2383 | G15: 2302 | J15: Trade Receivables (Billed and Unbilled) | K15: =$D15/$D$22 -> 0.25853122 | L15: =$E15/$E$22 -> 0.25721467 | M15: =$F15/$F$22 -> 0.2489813 | N15: =$G15/$G$22 -> 0.26390003
C16: Cash and Cash Equivalents | D16: 1150 | E16: 1021 | F16: 81 | G16: 27 | J16: Cash and Cash Equivalents | K16: =$D16/$D$22 -> 0.090423022 | L16: =$E16/$E$22 -> 0.095047477 | M16: =$F16/$F$22 -> 0.0084630655 | N16: =$G16/$G$22 -> 0.0030952654
C17: *Other Non-Current Assets | D17: 2074 | E17: 1171 | F17: 1528 | G17: 697 | J17: *Other Non-Current Assets | K17: =$D17/$D$22 -> 0.16307596 | L17: =$E17/$E$22 -> 0.10901136 | M17: =$F17/$F$22 -> 0.15964894 | N17: =$G17/$G$22 -> 0.079903703
C18: Total Current Assets | D18: =D14+D15+D16+D17 -> 8817 | E18: =SUM(E14:E17) -> 7018 | F18: =SUM(F14:F17) -> 6222 | G18: =SUM(G14:G17) -> 5190 | J18: Total Current Assets | K18: =$D18/$D$22 -> 0.69326938 | L18: =$E18/$E$22 -> 0.6533234 | M18: =$F18/$F$22 -> 0.65008881 | N18: =$G18/$G$22 -> 0.59497879
B20: Total Assets | D20: =D12+D18 -> 12718 | E20: =E12+E18 -> 10742 | F20: =F12+F18 -> 9571 | G20: =G12+G18 -> 8723 | I20: Total Assets | K20: =D20/D20 -> 1 | L20: =E20/E20 -> 1 | M20: =F20/F20 -> 1 | N20: =G20/G20 -> 1
B22: Total Assets | D22: =D12+D18 -> 12718 | E22: =E12+E18 -> 10742 | F22: =F12+F18 -> 9571 | G22: =G12+G18 -> 8723 | I22: Total Assets | K22: =D22/D22 -> 1 | L22: =E22/E22 -> 1 | M22: =F22/F22 -> 1 | N22: =G22/G22 -> 1
B24: EQUITY & LIABILITY | I24: EQUITY & LIABILITY
B26: Equity | C26: Share Capital | D26: 145 | E26: 145 | F26: 145 | G26: 145 | I26: Equity | J26: Share Capital | K26: =$D26/$D$42 -> 0.011401164 | L26: =$E26/$E$42 -> 0.013498417 | M26: =$F26/$F$42 -> 0.015149932 | N26: =$G26/$G$42 -> 0.016622722
C27: Other equity | D27: 7734 | E27: 6818 | F27: 5799 | G27: 4747 | J27: Other equity | K27: =$D27/$D$42 -> 0.60811448 | L27: =$E27/$E$42 -> 0.6347049 | M27: =$F27/$F$42 -> 0.6058928 | N27: =$G27/$G$42 -> 0.54419351
C28: Total Equity | D28: =D26+D27 -> 7879 | E28: =E26+E27 -> 6963 | F28: =F26+F27 -> 5944 | G28: =G26+G27 -> 4892 | J28: Total Equity | K28: =$D28/$D$42 -> 0.61951565 | L28: =$E28/$E$42 -> 0.64820331 | M28: =$F28/$F$42 -> 0.62104273 | N28: =$G28/$G$42 -> 0.56081623
B30: Total Equity | D30: =D26+D27 -> 7879 | E30: =E26+E27 -> 6963 | F30: =F26+F27 -> 5944 | G30: =G26+G27 -> 4892 | I30: Total Equity | K30: =$D30/$D$42 -> 0.61951565 | L30: =$E30/$E$42 -> 0.64820331 | M30: =$F30/$F$42 -> 0.62104273 | N30: =$G30/$G$42 -> 0.56081623
B32: Non-Current Liabilities | C32: Provisions | D32: 16 | E32: 15 | F32: 12 | G32: 15 | I32: Non-Current Liabilities | J32: Provisions | K32: =$D32/$D$42 -> 0.0012580594 | L32: =$E32/$E$42 -> 0.001396388 | M32: =$F32/$F$42 -> 0.0012537875 | N32: =$G32/$G$42 -> 0.0017195919
C33: *Other Non-Current Liabilities | D33: 334 | E33: 137 | F33: 80 | G33: 135 | J33: *Other Non-Current Liabilities | K33: =$D33/$D$42 -> 0.026261991 | L33: =$E33/$E$42 -> 0.012753677 | M33: =$F33/$F$42 -> 0.0083585832 | N33: =$G33/$G$42 -> 0.015476327
C34: Total Non-Current Liabilities | D34: =D32+D33 -> 350 | E34: =E32+E33 -> 152 | F34: =F32+F33 -> 92 | G34: =G32+G33 -> 150 | J34: Total Non-Current Liabilities | K34: =$D34/$D$42 -> 0.02752005 | L34: =$E34/$E$42 -> 0.014150065 | M34: =$F34/$F$42 -> 0.0096123707 | N34: =$G34/$G$42 -> 0.017195919
B36: Current Liabilities | C36: Trade payables | D36: 2152 | E36: 1827 | F36: 1738 | G36: 1528 | I36: Current Liabilities | J36: Trade payables | K36: =$D36/$D$42 -> 0.169209 | L36: =$E36/$E$42 -> 0.17008006 | M36: =$F36/$F$42 -> 0.18159022 | N36: =$G36/$G$42 -> 0.17516909
C37: *Other Current Liabilities | D37: 2337 | E37: 1800 | F37: 1797 | G37: 2153 | J37: *Other Current Liabilities | K37: =$D37/$D$42 -> 0.18375531 | L37: =$E37/$E$42 -> 0.16756656 | M37: =$F37/$F$42 -> 0.18775468 | N37: =$G37/$G$42 -> 0.24681876
C38: Total Current Liabilities | D38: =D36+D37 -> 4489 | E38: =E36+E37 -> 3627 | F38: =F36+F37 -> 3535 | G38: =G36+G37 -> 3681 | J38: Total Current Liabilities | K38: =$D38/$D$42 -> 0.3529643 | L38: =$E38/$E$42 -> 0.33764662 | M38: =$F38/$F$42 -> 0.3693449 | N38: =$G38/$G$42 -> 0.42198785
B40: Total Liability | D40: =D34+D38 -> 4839 | E40: =E34+E38 -> 3779 | F40: =F34+F38 -> 3627 | G40: =G34+G38 -> 3831 | I40: Total Liability | K40: =$D40/$D$42 -> 0.38048435 | L40: =$E40/$E$42 -> 0.35179669 | M40: =$F40/$F$42 -> 0.37895727 | N40: =$G40/$G$42 -> 0.43918377
B42: Total Equity and Liability | D42: =D30+D40 -> 12718 | E42: =E30+E40 -> 10742 | F42: =F30+F40 -> 9571 | G42: =G30+G40 -> 8723 | I42: Total Equity and Liability | K42: =D42/D42 -> 1 | L42: =E42/E42 -> 1 | M42: =F42/F42 -> 1 | N42: =G42/G42 -> 1

Sheet Liquidity Ratio
B3: Current Ratio
B4: Company Name | C4: March 31, 2025 | D4: March 31, 2024 | E4: March 31, 2023 | F4: March 31, 2022
B5: United Spirits | C5: ='United Spirits BS'!D18/'United Spirits BS'!D38 -> 1.9641346 | D5: ='United Spirits BS'!E18/'United Spirits BS'!E38 -> 1.9349325 | E5: ='United Spirits BS'!F18/'United Spirits BS'!F38 -> 1.7601132 | F5: ='United Spirits BS'!G18/'United Spirits BS'!G38 -> 1.409943
B6: Baseline | C6: 1 | D6: 1 | E6: 1 | F6: 1
B9: Acid-Test (Quick) Ratio
B10: Company Name | C10: March 31, 2025 | D10: March 31, 2024 | E10: March 31, 2023 | F10: March 31, 2022
B11: United Spirits | C11: =('United Spirits BS'!D18-'United Spirits BS'!D14)/'United Spirits BS'!D38 -> 1.4506572 | D11: =('United Spirits BS'!E18-'United Spirits BS'!E14)/'United Spirits BS'!E38 -> 1.3661428 | E11: =('United Spirits BS'!F18-'United Spirits BS'!F14)/'United Spirits BS'!F38 -> 1.1292786 | F11: =('United Spirits BS'!G18-'United Spirits BS'!G14)/'United Spirits BS'!G38 -> 0.82205922
B12: Baseline | C12: 1 | D12: 1 | E12: 1 | F12: 1
B15: Cash Ratio
B16: Company Name | C16: March 31, 2025 | D16: March 31, 2024 | E16: March 31, 2023 | F16: March 31, 2022
B17: United Spirits | C17: ='United Spirits BS'!D16/'United Spirits BS'!D38 -> 0.25618178 | D17: ='United Spirits BS'!E16/'United Spirits BS'!E38 -> 0.28149986 | E17: ='United Spirits BS'!F16/'United Spirits BS'!F38 -> 0.02291372 | F17: ='United Spirits BS'!G16/'United Spirits BS'!G38 -> 0.0073349633
B18: Baseline | C18: 0.5 | D18: 0.5 | E18: 0.5 | F18: 0.5

Sheet Activity Ratio
B3: Accounts Receivable Turnover Ratio (ART) | H3: Fixed Asset Turnover Ratio (FAT)
B4: Company Name | C4: March 31, 2025 | D4: March 31, 2024 | E4: March 31, 2023 | F4: March 31, 2022 | H4: Company Name | I4: March 31, 2025 | J4: March 31, 2024 | K4: March 31, 2023 | L4: March 31, 2022
B5: United Spirits | C5: ='United Spirits IS'!D5/'United Spirits BS'!D15 -> 8.1447689 | D5: ='United Spirits IS'!E5/'United Spirits BS'!E15 -> 9.1889251 | E5: ='United Spirits IS'!F5/'United Spirits BS'!F15 -> 11.572807 | F5: ='United Spirits IS'!G5/'United Spirits BS'!G15 -> 13.367941 | H5: United Spirits | I5: ='United Spirits IS'!D7/'United Spirits BS'!D8 -> 32.007059 | J5: ='United Spirits IS'!E7/'United Spirits BS'!E8 -> 30.478673 | K5: ='United Spirits IS'!F7/'United Spirits BS'!F8 -> 28.274029 | L5: ='United Spirits IS'!G7/'United Spirits BS'!G8 -> 25.651124
B6: Formula | C6: Revenue from Operations / Trade Receivables | H6: Formula | I6: Total Revenue / Property, Plant and Equipment (PPE)
B10: Days in Receivables (DSO) | H10: Total Asset Turnover Ratio (TAT)
B11: Company Name | C11: March 31, 2025 | D11: March 31, 2024 | E11: March 31, 2023 | F11: March 31, 2022 | H11: Company Name | I11: March 31, 2025 | J11: March 31, 2024 | K11: March 31, 2023 | L11: March 31, 2022
B12: United Spirits | C12: =365/C5 -> 44.81404 | D12: =365/D5 -> 39.72173 | E12: =365/E5 -> 31.539452 | F12: =365/F5 -> 27.30413 | H12: United Spirits | I12: ='United Spirits IS'!D7/'United Spirits BS'!D22 -> 2.1391728 | J12: ='United Spirits IS'!E7/'United Spirits BS'!E22 -> 2.3947123 | K12: ='United Spirits IS'!F7/'United Spirits BS'!F22 -> 2.8891443 | L12: ='United Spirits IS'!G7/'United Spirits BS'!G22 -> 3.5316978
B13: Formula | C13: 365 / Accounts Receivable Turnover Ratio (ART) | H13: Formula | I13: Total Revenue / Total Assets

Sheet Profitability Ratio
B3: Gross Profit Margin | H3: Return on Equity (ROE)
B4: Company Name | C4: March 31, 2025 | D4: March 31, 2024 | E4: March 31, 2023 | F4: March 31, 2022 | H4: Company Name | I4: March 31, 2025 | J4: March 31, 2024 | K4: March 31, 2023 | L4: March 31, 2022
B5: United Spirits | C5: ='United Spirits IS'!D13/'United Spirits IS'!D7 -> 0.20591046 | D5: ='United Spirits IS'!E13/'United Spirits IS'!E7 -> 0.19355466 | E5: ='United Spirits IS'!F13/'United Spirits IS'!F7 -> 0.15825257 | F5: ='United Spirits IS'!G13/'United Spirits IS'!G7 -> 0.13552115 | H5: United Spirits | I5: ='United Spirits IS'!D28/'United Spirits BS'!D30 -> 0.19774083 | J5: ='United Spirits IS'!E28/'United Spirits BS'!E30 -> 0.18842453 | K5: ='United Spirits IS'!F28/'United Spirits BS'!F30 -> 0.1769852 | L5: ='United Spirits IS'!G28/'United Spirits BS'!G30 -> 0.17395748
B6: Formula | C6: Gross Profit / Total Revenue | H6: Formula | I6: Profit After Tax (PAT) / Total Equity
B9: Operating Profit (EBIT) Margin | H9: Return on Asset (ROA)
B10: Company Name | C10: March 31, 2025 | D10: March 31, 2024 | E10: March 31, 2023 | F10: March 31, 2022 | H10: Company Name | I10: March 31, 2025 | J10: March 31, 2024 | K10: March 31, 2023 | L10: March 31, 2022
B11: United Spirits | C11: ='United Spirits IS'!D19/'United Spirits IS'!D7 -> 0.081232081 | D11: ='United Spirits IS'!E19/'United Spirits IS'!E7 -> 0.069157207 | E11: ='United Spirits IS'!F19/'United Spirits IS'!F7 -> 0.044192102 | F11: ='United Spirits IS'!G19/'United Spirits IS'!G7 -> 0.040769955 | H11: United Spirits | I11: ='United Spirits IS'!D28/'United Spirits BS'!D22 -> 0.12250354 | J11: ='United Spirits IS'!E28/'United Spirits BS'!E22 -> 0.1221374 | K11: ='United Spirits IS'!F28/'United Spirits BS'!F22 -> 0.10991537 | L11: ='United Spirits IS'!G28/'United Spirits BS'!G22 -> 0.09755818
B12: Formula | C12: EBIT / Total Revenue | H12: Formula | I12: Profit After Tax (PAT) / Total Asset
B15: Net Profit Margin | H15: Return on Captial Employed (ROCE)
B16: Company Name | C16: March 31, 2025 | D16: March 31, 2024 | E16: March 31, 2023 | F16: March 31, 2022 | H16: Company Name | I16: March 31, 2025 | J16: March 31, 2024 | K16: March 31, 2023 | L16: March 31, 2022
B17: United Spirits | C17: ='United Spirits IS'!D28/'United Spirits IS'!D7 -> 0.057266779 | D17: ='United Spirits IS'!E28/'United Spirits IS'!E7 -> 0.051002954 | E17: ='United Spirits IS'!F28/'United Spirits IS'!F7 -> 0.038044264 | F17: ='United Spirits IS'!G28/'United Spirits IS'!G7 -> 0.027623592 | H17: United Spirits | I17: ='United Spirits IS'!D19/('United Spirits BS'!D30+'United Spirits BS'!D40) -> 0.17376946 | J17: ='United Spirits IS'!E19/('United Spirits BS'!E30+'United Spirits BS'!E40) -> 0.16561162 | K17: ='United Spirits IS'!F19/('United Spirits BS'!F30+'United Spirits BS'!F40) -> 0.12767736 | L17: ='United Spirits IS'!G19/('United Spirits BS'!G30+'United Spirits BS'!G40) -> 0.14398716
B18: Formula | C18: Profit After Tax (PAT) / Total Revenue | H18: Formula | I18: EBIT / (Total Equity+Total Liabilities)

Sheet Solvency Ratio
B3: Asset to Equity Multiplier (AEM)
B4: Company Name | C4: March 31, 2025 | D4: March 31, 2024 | E4: March 31, 2023 | F4: March 31, 2022
B5: United Spirits | C5: ='United Spirits BS'!D22/'United Spirits BS'!D30 -> 1.6141642 | D5: ='United Spirits BS'!E22/'United Spirits BS'!E30 -> 1.5427258 | E5: ='United Spirits BS'!F22/'United Spirits BS'!F30 -> 1.6101952 | F5: ='United Spirits BS'!G22/'United Spirits BS'!G30 -> 1.7831153
B6: Formula | C6: Total Assets / Total Equity
B9: Debt-to-Equity Ratio
B10: Company Name | C10: March 31, 2025 | D10: March 31, 2024 | E10: March 31, 2023 | F10: March 31, 2022
B11: United Spirits | C11: ='United Spirits BS'!D40/'United Spirits BS'!D30 -> 0.61416423 | D11: ='United Spirits BS'!E40/'United Spirits BS'!E30 -> 0.54272584 | E11: ='United Spirits BS'!F40/'United Spirits BS'!F30 -> 0.61019515 | F11: ='United Spirits BS'!G40/'United Spirits BS'!G30 -> 0.78311529
B12: Formula | C12: Total Liabilities / Total Equity
B15: Interest Coverage Ratio (ICR)
B16: Company Name | C16: March 31, 2025 | D16: March 31, 2024 | E16: March 31, 2023 | F16: March 31, 2022
B17: United Spirits | C17: ='United Spirits IS'!D19/'United Spirits IS'!D21 -> 24.831461 | D17: ='United Spirits IS'!E19/'United Spirits IS'!E21 -> 23.407895 | E17: ='United Spirits IS'!F19/'United Spirits IS'!F21 -> 11.75 | F17: ='United Spirits IS'!G19/'United Spirits IS'!G21 -> 14.272727
B18: Formula | C18: EBIT / Interest

Sheet Valuation Ratio
B3: Earnings Per Share (EPS) | H3: Enterprise Value-to-EBITDA (EV/EBITDA)
B4: Company Name | C4: March 31, 2025 | D4: March 31, 2024 | E4: March 31, 2023 | F4: March 31, 2022 | H4: Company Name | I4: March 31, 2025 | J4: March 31, 2024 | K4: March 31, 2023 | L4: March 31, 2022
B5: United Spirits | C5: ='United Spirits IS'!D28/I11 -> 21.430536 | D5: ='United Spirits IS'!E28/J11 -> 18.046768 | E5: ='United Spirits IS'!F28/K11 -> 14.470426 | F5: ='United Spirits IS'!G28/L11 -> 11.70564 | H5: United Spirits | I5: =((I11*I16)+'United Spirits BS'!D40-'United Spirits BS'!D16)/('United Spirits IS'!D19+'United Spirits IS'!D16) -> 43.922705 | J5: =((J11*J16)+'United Spirits BS'!E40-'United Spirits BS'!E16)/('United Spirits IS'!E19+'United Spirits IS'!E16) -> 40.493392 | K5: =((K11*K16)+'United Spirits BS'!F40-'United Spirits BS'!F16)/('United Spirits IS'!F19+'United Spirits IS'!F16) -> 46.199598 | L5: =((L11*L16)+'United Spirits BS'!G40-'United Spirits BS'!G16)/('United Spirits IS'!G19+'United Spirits IS'!G16) -> 39.165049
B6: Formula | C6: Profit After Tax (PAT) / Shares Outstanding | H6: Formula | I6: Market Cap+Debt−Cash / EBIT+Depreciation
B9: Price-to-Earnings (P/E) Ratio | H9: Shares Outstanding (in crore)
B10: Company Name | C10: March 31, 2025 | D10: March 31, 2024 | E10: March 31, 2023 | F10: March 31, 2022 | H10: Company Name | I10: March 31, 2025 | J10: March 31, 2024 | K10: March 31, 2023 | L10: March 31, 2022
B11: United Spirits | C11: =I16/C5 -> 67.660462 | D11: =J16/D5 -> 60.952744 | E11: =K16/E5 -> 62.195817 | F11: =L16/F5 -> 66.634548 | H11: United Spirits | I11: 72.7 | J11: 72.7 | K11: 72.7 | L11: 72.7
B12: Formula | C12: Market Price / EPS
H14: Current Market Price
B15: Price-to-Sales (P/S) Ratio | H15: Company Name | I15: March 31, 2025 | J15: March 31, 2024 | K15: March 31, 2023 | L15: March 31, 2022
B16: Company Name | C16: March 31, 2025 | D16: March 31, 2024 | E16: March 31, 2023 | F16: March 31, 2022 | H16: United Spirits | I16: 1450 | J16: 1100 | K16: 900 | L16: 780
B17: United Spirits | C17: =(I11*I16)/'United Spirits IS'!D7 -> 3.8746968 | D17: =(J11*J16)/'United Spirits IS'!E7 -> 3.10877 | E17: =(K11*K16)/'United Spirits IS'!F7 -> 2.3661941 | F17: =(L11*L16)/'United Spirits IS'!G7 -> 1.8406856
B18: Formula | C18: Market Capitalization / Total Revenue

Sheet DuPont Analysis
